{"name":"Mongolia","code":"MN","capital":"Ulan Bator","region":"AS","currency":{"code":"MNT","name":"Mongolian t\u00f6gr\u00f6g","symbol":"\u20ae"},"language":{"code":"mn","name":"Mongolian"},"emoji":"\ud83c\uddf2\ud83c\uddf3","state":["Bulgan Province","Darkhan-Uul Province","Dornod Province","Khovd Province","\u00d6v\u00f6rkhangai Province","Orkhon Province","\u00d6mn\u00f6govi Province","T\u00f6v Province","Bayan-\u00d6lgii Province","Dundgovi Province","Uvs Province","Govi-Altai Province","Arkhangai Province","Khentii Province","Kh\u00f6vsg\u00f6l Province","Bayankhongor Province","S\u00fckhbaatar Province","Govis\u00fcmber Province","Zavkhan Province","Selenge Province","Dornogovi Province"],"dialling_code":"+976","isoCode":"496"}